missav_api/__init__.py
missav_api/missav_api.py
missav_api/modules/__init__.py
missav_api/modules/consts.py
missav_api/tests/__init__.py
missav_api/tests/conftest.py
missav_api/tests/test_all.py
missAV_api_async-1.2.dist-info/METADATA
missAV_api_async-1.2.dist-info/WHEEL
missAV_api_async-1.2.dist-info/top_level.txt
missAV_api_async-1.2.dist-info/RECORD
