Metadata-Version: 2.1
Name: missAV_api-async
Version: 1.2
Summary: A Python API for the Porn Site missav.com
Home-page: https://github.com/EchterAlsFake/missAV_api
Author: Johannes Habel
Author-email: EchterAlsFake@proton.me
License: LGPLv3
Classifier: License :: OSI Approved :: GNU Lesser General Public License v3 (LGPLv3)
Classifier: Programming Language :: Python
Requires-Dist: eaf_base_api-async
